ansible_plan/__init__.py
ansible_plan/__main__.py
ansible_plan/cli.py
ansible_plan/service.py
ansible_plan/core/__init__.py
ansible_plan/core/engine.py
ansible_plan/core/exceptions.py
ansible_plan/core/loader.py
ansible_plan/core/models.py
ansible_plan/core/validation.py
ansible_plan/schemas/v1.json
ansible_plan/ui/__init__.py
ansible_plan/ui/api_client.py
ansible_plan/ui/base.py
ansible_plan/ui/stdout.py
ansible_plan/ui/style.css
ansible_plan/ui/textual.py
ansible_plan-0.1.3.dist-info/METADATA
ansible_plan-0.1.3.dist-info/WHEEL
ansible_plan-0.1.3.dist-info/entry_points.txt
ansible_plan-0.1.3.dist-info/licenses/AUTHORS
ansible_plan-0.1.3.dist-info/licenses/LICENSE
ansible_plan-0.1.3.dist-info/RECORD
