Metadata-Version: 2.4
Name: ansible-plan
Version: 0.1.3
Summary: A command-line tool for launching workflows composed of Red Hat Ansible® playbooks
Project-URL: Documentation, https://github.com/BartokIT/ansible-plan/blob/main/README.md
Project-URL: Repository, https://github.com/BartokIT/ansible-plan
Project-URL: Issues, https://github.com/BartokIT/ansible-plan/issues
Author: BartokIT
License:                     GNU AFFERO GENERAL PUBLIC LICENSE
License-File: AUTHORS
License-File: LICENSE
Requires-Python: >=3.8
Requires-Dist: ansible
Requires-Dist: fastapi
Requires-Dist: httpx
Requires-Dist: jinja2
Requires-Dist: networkx
Requires-Dist: rich
Requires-Dist: textual
Requires-Dist: uvicorn
